ldesign/__init__.py
ldesign/_version.py
ldesign/calculation.py
ldesign/chips.py
ldesign/config.py
ldesign/elements.py
ldesign/path.py
ldesign/planning.py
ldesign/utils.py
ldesign/shapes/__init__.py
ldesign/shapes/bondpad.py
ldesign/shapes/boundary.py
ldesign/shapes/crossover.py
ldesign/shapes/floating_qubit.py
ldesign/shapes/junction.py
ldesign/shapes/marker.py
ldesign/shapes/path.py
ldesign/shapes/tpad.py
ldesign/shapes/upad.py
ldesign/shapes/xmon.py
ldesign-0.1.0.dist-info/LICENSE
ldesign-0.1.0.dist-info/METADATA
ldesign-0.1.0.dist-info/WHEEL
ldesign-0.1.0.dist-info/top_level.txt
ldesign-0.1.0.dist-info/RECORD
