Metadata-Version: 2.1
Name: ldesign
Version: 0.1.0
Summary: Layout design tool for superconducting circuits based on gdstk.
Author-email: Jiahao Yuan <kaho0769@qq.com>
License: MIT License        
Project-URL: Homepage, https://github.com/kahojyun/ldesign
Project-URL: Bug Tracker, https://github.com/kahojyun/ldesign/issues
Keywords: layout,gdsii
Classifier: Programming Language :: Python :: 3
Classifier: License :: OSI Approved :: MIT License
Classifier: Operating System :: OS Independent
Requires-Python: >=3.10
License-File: LICENSE
Requires-Dist: gdstk (~=0.8.3)
Requires-Dist: gdspy
Requires-Dist: numpy
Requires-Dist: scipy
Provides-Extra: dev
Requires-Dist: black ; extra == 'dev'
